{"positionName": "18435-风控总监（深圳）", "publishTime": "2018-06-10", "positionLink": "position_detail.php?id=23360&keywords=&tid=0&lid=0", "peopleNum": "1", "positionType": "技术类", "workLocation": "深圳"}
{"positionName": "OMG236-视频体验优化算法工程师 （深圳）", "publishTime": "2018-06-10", "positionLink": "position_detail.php?id=23193&keywords=&tid=0&lid=0", "peopleNum": "1", "positionType": "技术类", "workLocation": "深圳"}
{"positionName": "19822-影视策划经理", "publishTime": "2018-06-10", "positionLink": "position_detail.php?id=22686&keywords=&tid=0&lid=0", "peopleNum": "2", "positionType": "产品/项目类", "workLocation": "北京"}
{"positionName": "SNG10-视觉设计组长（深圳）", "publishTime": "2018-06-10", "positionLink": "position_detail.php?id=18606&keywords=&tid=0&lid=0", "peopleNum": "2", "positionType": "设计类", "workLocation": "深圳"}
{"positionName": "TEG09-虚拟化研发工程师（深圳）", "publishTime": "2018-06-10", "positionLink": "position_detail.php?id=22746&keywords=&tid=0&lid=0", "peopleNum": "2", "positionType": "技术类", "workLocation": "深圳"}
{"positionName": "TEG10-资源规划师（深圳）", "publishTime": "2018-06-10", "positionLink": "position_detail.php?id=21470&keywords=&tid=0&lid=0", "peopleNum": "1", "positionType": "技术类", "workLocation": "深圳"}
{"positionName": "TEG13-C++后台开发工程师（深圳）", "publishTime": "2018-06-10", "positionLink": "position_detail.php?id=20040&keywords=&tid=0&lid=0", "peopleNum": "3", "positionType": "技术类", "workLocation": "深圳"}
{"positionName": "SNG01-QQ高级产品经理（深圳）", "publishTime": "2018-06-10", "positionLink": "position_detail.php?id=16860&keywords=&tid=0&lid=0", "peopleNum": "3", "positionType": "产品/项目类", "workLocation": "深圳"}
{"positionName": "TEG04-腾讯乐享Web前端开发工程师（深圳）", "publishTime": "2018-06-10", "positionLink": "position_detail.php?id=41351&keywords=&tid=0&lid=0", "peopleNum": "2", "positionType": "技术类", "workLocation": "深圳"}
{"positionName": "27216-金融公共事业创新产品策划经理（深圳）", "publishTime": "2018-06-10", "positionLink": "position_detail.php?id=41352&keywords=&tid=0&lid=0", "peopleNum": "1", "positionType": "产品/项目类", "workLocation": "深圳"}
{"positionName": "15575-《王者荣耀》公共事务经理（深圳）", "publishTime": "2018-06-10", "positionLink": "position_detail.php?id=41354&keywords=&tid=0&lid=0", "peopleNum": "1", "positionType": "产品/项目类", "workLocation": "深圳"}
{"positionName": "27730-品牌策划经理", "publishTime": "2018-06-10", "positionLink": "position_detail.php?id=41341&keywords=&tid=0&lid=0", "peopleNum": "1", "positionType": "市场类", "workLocation": "北京"}
{"positionName": "OMG192-品牌广告媒介岗位", "publishTime": "2018-06-10", "positionLink": "position_detail.php?id=41343&keywords=&tid=0&lid=0", "peopleNum": "1", "positionType": "市场类", "workLocation": "北京"}
{"positionName": "WXG02-113 微信后台开发工程师（广州）", "publishTime": "2018-06-10", "positionLink": "position_detail.php?id=41344&keywords=&tid=0&lid=0", "peopleNum": "1", "positionType": "技术类", "workLocation": "广州"}
{"positionName": "SNG04-QQ看点高级产品经理-垂直类目运营机制（深圳）", "publishTime": "2018-06-10", "positionLink": "position_detail.php?id=41345&keywords=&tid=0&lid=0", "peopleNum": "2", "positionType": "产品/项目类", "workLocation": "深圳"}
{"positionName": "SNG04-看点内容运营（深圳）", "publishTime": "2018-06-10", "positionLink": "position_detail.php?id=41346&keywords=&tid=0&lid=0", "peopleNum": "2", "positionType": "产品/项目类", "workLocation": "深圳"}
{"positionName": "18425-信用卡还款产品策划经理（深圳）", "publishTime": "2018-06-10", "positionLink": "position_detail.php?id=41348&keywords=&tid=0&lid=0", "peopleNum": "1", "positionType": "产品/项目类", "workLocation": "深圳"}
{"positionName": "20503-腾讯优图市场策划（上海）", "publishTime": "2018-06-10", "positionLink": "position_detail.php?id=41335&keywords=&tid=0&lid=0", "peopleNum": "1", "positionType": "市场类", "workLocation": "上海"}
{"positionName": "SNG11-云安全金融行业产品经理（深圳）", "publishTime": "2018-06-10", "positionLink": "position_detail.php?id=41366&keywords=&tid=0&lid=0", "peopleNum": "1", "positionType": "产品/项目类", "workLocation": "深圳"}
{"positionName": "15575-《王者荣耀》内容传播运营（深圳/成都）", "publishTime": "2018-06-10", "positionLink": "position_detail.php?id=41353&keywords=&tid=0&lid=0", "peopleNum": "1", "positionType": "产品/项目类", "workLocation": "深圳"}
{"positionName": "15575-《王者荣耀》数值策划（成都）", "publishTime": "2018-06-10", "positionLink": "position_detail.php?id=41355&keywords=&tid=0&lid=0", "peopleNum": "1", "positionType": "产品/项目类", "workLocation": "成都"}
{"positionName": "SA-腾讯社交广告公众号广告流量运营经理（微信广告 深圳）", "publishTime": "2018-06-10", "positionLink": "position_detail.php?id=41356&keywords=&tid=0&lid=0", "peopleNum": "2", "positionType": "产品/项目类", "workLocation": "深圳"}
{"positionName": "22850-腾讯视频VIP福利社运营", "publishTime": "2018-06-10", "positionLink": "position_detail.php?id=41357&keywords=&tid=0&lid=0", "peopleNum": "1", "positionType": "市场类", "workLocation": "北京"}
{"positionName": "SNG11-云安全高级Web前端开发工程师（深圳）", "publishTime": "2018-06-10", "positionLink": "position_detail.php?id=41358&keywords=&tid=0&lid=0", "peopleNum": "1", "positionType": "技术类", "workLocation": "深圳"}
{"positionName": "20503-安防线AI后端开发工程师（上海）", "publishTime": "2018-06-10", "positionLink": "position_detail.php?id=41360&keywords=&tid=0&lid=0", "peopleNum": "2", "positionType": "技术类", "workLocation": "上海"}
{"positionName": "25666-教育云商务拓展（北京）", "publishTime": "2018-06-10", "positionLink": "position_detail.php?id=41347&keywords=&tid=0&lid=0", "peopleNum": "2", "positionType": "市场类", "workLocation": "深圳"}
{"positionName": "23672-腾讯新闻深度报道记者（北京）", "publishTime": "2018-06-10", "positionLink": "position_detail.php?id=41349&keywords=&tid=0&lid=0", "peopleNum": "1", "positionType": "内容编辑类", "workLocation": "北京"}
{"positionName": "TEG04-腾讯乐享Web后台高级开发工程师（深圳）", "publishTime": "2018-06-10", "positionLink": "position_detail.php?id=41350&keywords=&tid=0&lid=0", "peopleNum": "2", "positionType": "技术类", "workLocation": "深圳"}
{"positionName": "23294-互娱电竞明星经纪组长（深圳）", "publishTime": "2018-06-10", "positionLink": "position_detail.php?id=41369&keywords=&tid=0&lid=0", "peopleNum": "1", "positionType": "市场类", "workLocation": "深圳"}
{"positionName": "21527-腾讯音乐数据库运维工程师（深圳）", "publishTime": "2018-06-10", "positionLink": "position_detail.php?id=41370&keywords=&tid=0&lid=0", "peopleNum": "1", "positionType": "技术类", "workLocation": "深圳"}
{"positionName": "19823-动画电影表演设计（深圳）", "publishTime": "2018-06-10", "positionLink": "position_detail.php?id=41371&keywords=&tid=0&lid=0", "peopleNum": "2", "positionType": "设计类", "workLocation": "深圳"}
{"positionName": "21228-游戏IP运营（深圳）", "publishTime": "2018-06-10", "positionLink": "position_detail.php?id=41372&keywords=&tid=0&lid=0", "peopleNum": "1", "positionType": "产品/项目类", "workLocation": "深圳"}
{"positionName": "21309-腾讯课堂平台内容运营高级经理（深圳）", "publishTime": "2018-06-10", "positionLink": "position_detail.php?id=41374&keywords=&tid=0&lid=0", "peopleNum": "2", "positionType": "产品/项目类", "workLocation": "深圳"}
{"positionName": "MIG07-网游加速器高级开发工程师", "publishTime": "2018-06-10", "positionLink": "position_detail.php?id=41359&keywords=&tid=0&lid=0", "peopleNum": "1", "positionType": "技术类", "workLocation": "深圳"}
{"positionName": "SNG04-QQ看点内容平台后台开发工程师", "publishTime": "2018-06-10", "positionLink": "position_detail.php?id=41361&keywords=&tid=0&lid=0", "peopleNum": "1", "positionType": "技术类", "workLocation": "上海"}
{"positionName": "SNG11-数据分析师（深圳）", "publishTime": "2018-06-10", "positionLink": "position_detail.php?id=41362&keywords=&tid=0&lid=0", "peopleNum": "2", "positionType": "技术类", "workLocation": "深圳"}
{"positionName": "SNG11-云安全生态合作经理（深圳）", "publishTime": "2018-06-10", "positionLink": "position_detail.php?id=41363&keywords=&tid=0&lid=0", "peopleNum": "1", "positionType": "产品/项目类", "workLocation": "深圳"}
{"positionName": "SNG11-云安全营销策划（深圳）", "publishTime": "2018-06-10", "positionLink": "position_detail.php?id=41364&keywords=&tid=0&lid=0", "peopleNum": "1", "positionType": "产品/项目类", "workLocation": "深圳"}
{"positionName": "18434-数据库营销总监(深圳)", "publishTime": "2018-06-10", "positionLink": "position_detail.php?id=41384&keywords=&tid=0&lid=0", "peopleNum": "1", "positionType": "市场类", "workLocation": "深圳"}
{"positionName": "27730-短视频渠道拓展经理（深圳）", "publishTime": "2018-06-10", "positionLink": "position_detail.php?id=41386&keywords=&tid=0&lid=0", "peopleNum": "2", "positionType": "产品/项目类", "workLocation": "深圳"}
{"positionName": "21309-腾讯课堂设计培训类目经理（深圳）", "publishTime": "2018-06-10", "positionLink": "position_detail.php?id=41373&keywords=&tid=0&lid=0", "peopleNum": "1", "positionType": "产品/项目类", "workLocation": "深圳"}
{"positionName": "MIG09-QQ浏览器游戏内容运营经理（深圳）", "publishTime": "2018-06-10", "positionLink": "position_detail.php?id=41375&keywords=&tid=0&lid=0", "peopleNum": "1", "positionType": "产品/项目类", "workLocation": "深圳"}
{"positionName": "21309-IT类目经理（深圳）", "publishTime": "2018-06-10", "positionLink": "position_detail.php?id=41376&keywords=&tid=0&lid=0", "peopleNum": "1", "positionType": "产品/项目类", "workLocation": "深圳"}
{"positionName": "EC-青少年编程教育教研（深圳）", "publishTime": "2018-06-10", "positionLink": "position_detail.php?id=41377&keywords=&tid=0&lid=0", "peopleNum": "1", "positionType": "产品/项目类", "workLocation": "深圳"}
{"positionName": "19332-企点产品高级运营经理（上海）", "publishTime": "2018-06-10", "positionLink": "position_detail.php?id=41378&keywords=&tid=0&lid=0", "peopleNum": "1", "positionType": "产品/项目类", "workLocation": "上海"}
{"positionName": "27730-互动产品运营（深圳）", "publishTime": "2018-06-10", "positionLink": "position_detail.php?id=41380&keywords=&tid=0&lid=0", "peopleNum": "3", "positionType": "产品/项目类", "workLocation": "深圳"}
{"positionName": "SNG11-云安全新零售行业产品经理（深圳）", "publishTime": "2018-06-10", "positionLink": "position_detail.php?id=41365&keywords=&tid=0&lid=0", "peopleNum": "1", "positionType": "产品/项目类", "workLocation": "深圳"}
{"positionName": "20503-安防线后台开发工程师（上海）", "publishTime": "2018-06-10", "positionLink": "position_detail.php?id=41368&keywords=&tid=0&lid=0", "peopleNum": "3", "positionType": "技术类", "workLocation": "上海"}
{"positionName": "18434-数据库营销经理(深圳)", "publishTime": "2018-06-10", "positionLink": "position_detail.php?id=41385&keywords=&tid=0&lid=0", "peopleNum": "1", "positionType": "市场类", "workLocation": "深圳"}
{"positionName": "27730-短视频合作拓展运营经理（深圳）", "publishTime": "2018-06-10", "positionLink": "position_detail.php?id=41387&keywords=&tid=0&lid=0", "peopleNum": "1", "positionType": "产品/项目类", "workLocation": "深圳"}
{"positionName": "WXG06-211 微信支付数据产品经理（深圳）", "publishTime": "2018-06-10", "positionLink": "position_detail.php?id=41388&keywords=&tid=0&lid=0", "peopleNum": "1", "positionType": "产品/项目类", "workLocation": "深圳"}
{"positionName": "25666-腾讯云业务拓展支持专员（深圳）", "publishTime": "2018-06-10", "positionLink": "position_detail.php?id=41391&keywords=&tid=0&lid=0", "peopleNum": "2", "positionType": "市场类", "workLocation": "深圳"}
{"positionName": "25666-腾讯云资深招投标&合同专家（北京/深圳）", "publishTime": "2018-06-10", "positionLink": "position_detail.php?id=41392&keywords=&tid=0&lid=0", "peopleNum": "4", "positionType": "市场类", "workLocation": "深圳"}
{"positionName": "21530-腾讯音乐HRBP（深圳）", "publishTime": "2018-06-10", "positionLink": "position_detail.php?id=41394&keywords=&tid=0&lid=0", "peopleNum": "1", "positionType": "职能类", "workLocation": "深圳"}
{"positionName": "19332-企点营销高级产品经理（上海）", "publishTime": "2018-06-10", "positionLink": "position_detail.php?id=41379&keywords=&tid=0&lid=0", "peopleNum": "1", "positionType": "产品/项目类", "workLocation": "上海"}
{"positionName": "AQ-法律研究合作经理（北京）", "publishTime": "2018-06-10", "positionLink": "position_detail.php?id=41381&keywords=&tid=0&lid=0", "peopleNum": "2", "positionType": "职能类", "workLocation": "北京"}
{"positionName": "AQ-数据安全研究合作经理（北京）", "publishTime": "2018-06-10", "positionLink": "position_detail.php?id=41382&keywords=&tid=0&lid=0", "peopleNum": "2", "positionType": "职能类", "workLocation": "北京"}
{"positionName": "26832-校园招聘经理（深圳）", "publishTime": "2018-06-10", "positionLink": "position_detail.php?id=41383&keywords=&tid=0&lid=0", "peopleNum": "1", "positionType": "职能类", "workLocation": "深圳"}
{"positionName": "25926-机器学习算法高级工程师", "publishTime": "2018-06-10", "positionLink": "position_detail.php?id=41404&keywords=&tid=0&lid=0", "peopleNum": "2", "positionType": "技术类", "workLocation": "深圳"}
{"positionName": "25926-游戏安全质量管理（深圳）", "publishTime": "2018-06-10", "positionLink": "position_detail.php?id=41405&keywords=&tid=0&lid=0", "peopleNum": "1", "positionType": "技术类", "workLocation": "深圳"}
{"positionName": "25926-游戏客户端安全工程师", "publishTime": "2018-06-10", "positionLink": "position_detail.php?id=41407&keywords=&tid=0&lid=0", "peopleNum": "1", "positionType": "技术类", "workLocation": "深圳"}
{"positionName": "SNG03-视频产品数据分析（深圳）", "publishTime": "2018-06-10", "positionLink": "position_detail.php?id=41393&keywords=&tid=0&lid=0", "peopleNum": "1", "positionType": "产品/项目类", "workLocation": "深圳"}
{"positionName": "SNG16-全民K歌Android开发工程师（深圳）", "publishTime": "2018-06-10", "positionLink": "position_detail.php?id=41395&keywords=&tid=0&lid=0", "peopleNum": "2", "positionType": "技术类", "workLocation": "深圳"}
{"positionName": "OMG148-大网总裁（北京）", "publishTime": "2018-06-10", "positionLink": "position_detail.php?id=41396&keywords=&tid=0&lid=0", "peopleNum": "1", "positionType": "内容编辑类", "workLocation": "北京"}
{"positionName": "15573-新侠风MMORPG手游客户端开发高级工程师（上海）", "publishTime": "2018-06-10", "positionLink": "position_detail.php?id=41397&keywords=&tid=0&lid=0", "peopleNum": "3", "positionType": "技术类", "workLocation": "上海"}
{"positionName": "15573-新侠风MMORPG后台开发高级工程师（上海）", "publishTime": "2018-06-10", "positionLink": "position_detail.php?id=41398&keywords=&tid=0&lid=0", "peopleNum": "1", "positionType": "技术类", "workLocation": "上海"}
{"positionName": "15573-新侠风MMORPG手游资深3D特效师（上海）", "publishTime": "2018-06-10", "positionLink": "position_detail.php?id=41400&keywords=&tid=0&lid=0", "peopleNum": "1", "positionType": "设计类", "workLocation": "上海"}
{"positionName": "SNG04-QQ看点推荐系统后台开发工程师（深圳）", "publishTime": "2018-06-10", "positionLink": "position_detail.php?id=41401&keywords=&tid=0&lid=0", "peopleNum": "2", "positionType": "技术类", "workLocation": "深圳"}
{"positionName": "SNG16-腾讯音乐IOS开发工程师（深圳）", "publishTime": "2018-06-10", "positionLink": "position_detail.php?id=41420&keywords=&tid=0&lid=0", "peopleNum": "10", "positionType": "技术类", "workLocation": "深圳"}
{"positionName": "25926-游戏安全测试工程师（深圳）", "publishTime": "2018-06-10", "positionLink": "position_detail.php?id=41406&keywords=&tid=0&lid=0", "peopleNum": "1", "positionType": "技术类", "workLocation": "深圳"}
{"positionName": "SNG08-QQ空间游戏及应用平台运营经理（深圳）", "publishTime": "2018-06-10", "positionLink": "position_detail.php?id=41408&keywords=&tid=0&lid=0", "peopleNum": "1", "positionType": "产品/项目类", "workLocation": "深圳"}
{"positionName": "OMG236-数据分析短视频推荐数据分析", "publishTime": "2018-06-10", "positionLink": "position_detail.php?id=41409&keywords=&tid=0&lid=0", "peopleNum": "2", "positionType": "技术类", "workLocation": "北京"}
{"positionName": "OMG097-高级系统测试工程师（北京）", "publishTime": "2018-06-10", "positionLink": "position_detail.php?id=41410&keywords=&tid=0&lid=0", "peopleNum": "2", "positionType": "技术类", "workLocation": "深圳"}
{"positionName": "OMG097-广告平台产品业务运维（上海）", "publishTime": "2018-06-10", "positionLink": "position_detail.php?id=41411&keywords=&tid=0&lid=0", "peopleNum": "1", "positionType": "技术类", "workLocation": "上海"}
{"positionName": "19332-企业产品视觉设计师", "publishTime": "2018-06-10", "positionLink": "position_detail.php?id=41413&keywords=&tid=0&lid=0", "peopleNum": "2", "positionType": "设计类", "workLocation": "上海"}
{"positionName": "15573-新侠风MMORPG手游高级策划（上海）", "publishTime": "2018-06-10", "positionLink": "position_detail.php?id=41399&keywords=&tid=0&lid=0", "peopleNum": "2", "positionType": "产品/项目类", "workLocation": "上海"}
{"positionName": "SA-腾讯社交广告大数据研发工程师（北京）", "publishTime": "2018-06-10", "positionLink": "position_detail.php?id=41402&keywords=&tid=0&lid=0", "peopleNum": "2", "positionType": "技术类", "workLocation": "北京"}
{"positionName": "SNG11-推荐算法高级研究员（深圳）", "publishTime": "2018-06-10", "positionLink": "position_detail.php?id=41403&keywords=&tid=0&lid=0", "peopleNum": "2", "positionType": "技术类", "workLocation": "深圳"}
{"positionName": "20761-内容管理高级经理（北京）", "publishTime": "2018-06-10", "positionLink": "position_detail.php?id=26572&keywords=&tid=0&lid=0", "peopleNum": "2", "positionType": "职能类", "workLocation": "北京"}
{"positionName": "OMG236-web前端开发工程师（深圳）", "publishTime": "2018-06-10", "positionLink": "position_detail.php?id=26436&keywords=&tid=0&lid=0", "peopleNum": "1", "positionType": "技术类", "workLocation": "深圳"}
{"positionName": "OMG236-移动端研发工程师（深圳）", "publishTime": "2018-06-10", "positionLink": "position_detail.php?id=26203&keywords=&tid=0&lid=0", "peopleNum": "1", "positionType": "技术类", "workLocation": "深圳"}
{"positionName": "OMG236-计算机视觉算法研发工程师（深圳）", "publishTime": "2018-06-10", "positionLink": "position_detail.php?id=26205&keywords=&tid=0&lid=0", "peopleNum": "1", "positionType": "技术类", "workLocation": "深圳"}
{"positionName": "21309-在线教育ios开发工程师（深圳）", "publishTime": "2018-06-10", "positionLink": "position_detail.php?id=26467&keywords=&tid=0&lid=0", "peopleNum": "2", "positionType": "技术类", "workLocation": "深圳"}
{"positionName": "21309-在线教育C/C++后台开发工程师（深圳）", "publishTime": "2018-06-10", "positionLink": "position_detail.php?id=26471&keywords=&tid=0&lid=0", "peopleNum": "10", "positionType": "技术类", "workLocation": "深圳"}
{"positionName": "20764-高级政府事务经理(广告方向)(北京)", "publishTime": "2018-06-10", "positionLink": "position_detail.php?id=26320&keywords=&tid=0&lid=0", "peopleNum": "1", "positionType": "职能类", "workLocation": "北京"}
{"positionName": "15573-游戏交互设计师(上海)", "publishTime": "2018-06-10", "positionLink": "position_detail.php?id=26107&keywords=&tid=0&lid=0", "peopleNum": "2", "positionType": "设计类", "workLocation": "上海"}
{"positionName": "OMG236-腾讯视频搜索后台研发工程师（深圳）", "publishTime": "2018-06-10", "positionLink": "position_detail.php?id=25689&keywords=&tid=0&lid=0", "peopleNum": "1", "positionType": "技术类", "workLocation": "深圳"}
{"positionName": "MIG07-系统安全研究员（北京）", "publishTime": "2018-06-10", "positionLink": "position_detail.php?id=25711&keywords=&tid=0&lid=0", "peopleNum": "3", "positionType": "技术类", "workLocation": "北京"}
{"positionName": "TEG14-运营开发工程师（深圳）", "publishTime": "2018-06-10", "positionLink": "position_detail.php?id=27099&keywords=&tid=0&lid=0", "peopleNum": "1", "positionType": "技术类", "workLocation": "深圳"}
{"positionName": "TEG07-CDC高级多媒体视觉设计师（深圳）", "publishTime": "2018-06-10", "positionLink": "position_detail.php?id=26624&keywords=&tid=0&lid=0", "peopleNum": "1", "positionType": "设计类", "workLocation": "深圳"}
{"positionName": "21309-在线教育高级web前端开发工程师（深圳）", "publishTime": "2018-06-10", "positionLink": "position_detail.php?id=26701&keywords=&tid=0&lid=0", "peopleNum": "8", "positionType": "技术类", "workLocation": "深圳"}
{"positionName": "20761-政策研究高级经理", "publishTime": "2018-06-10", "positionLink": "position_detail.php?id=26574&keywords=&tid=0&lid=0", "peopleNum": "2", "positionType": "职能类", "workLocation": "北京"}
{"positionName": "MIG09-商品推荐算法高级工程师", "publishTime": "2018-06-10", "positionLink": "position_detail.php?id=26589&keywords=&tid=0&lid=0", "peopleNum": "2", "positionType": "技术类", "workLocation": "深圳"}
{"positionName": "21309-在线教育JAVA后台开发工程师（深圳）", "publishTime": "2018-06-10", "positionLink": "position_detail.php?id=26470&keywords=&tid=0&lid=0", "peopleNum": "1", "positionType": "技术类", "workLocation": "深圳"}
{"positionName": "TEG12-IDC运营服务管理经理（深圳）", "publishTime": "2018-06-10", "positionLink": "position_detail.php?id=26490&keywords=&tid=0&lid=0", "peopleNum": "1", "positionType": "技术类", "workLocation": "深圳"}
{"positionName": "S2-高级风险管理和内部控制分析师（采购风控方向）", "publishTime": "2018-06-10", "positionLink": "position_detail.php?id=26513&keywords=&tid=0&lid=0", "peopleNum": "1", "positionType": "职能类", "workLocation": "深圳"}
{"positionName": "TEG17-深度学习研究员（深圳）", "publishTime": "2018-06-10", "positionLink": "position_detail.php?id=26544&keywords=&tid=0&lid=0", "peopleNum": "2", "positionType": "技术类", "workLocation": "深圳"}
{"positionName": "TEG13-自然语言处理高级工程师（北京）", "publishTime": "2018-06-10", "positionLink": "position_detail.php?id=26556&keywords=&tid=0&lid=0", "peopleNum": "2", "positionType": "技术类", "workLocation": "北京"}
{"positionName": "WXG06-211 微信支付餐饮行业运营经理（深圳）", "publishTime": "2018-06-10", "positionLink": "position_detail.php?id=27215&keywords=&tid=0&lid=0", "peopleNum": "1", "positionType": "产品/项目类", "workLocation": "深圳"}
{"positionName": "18428-金融应用高级运维工程师（深圳）", "publishTime": "2018-06-10", "positionLink": "position_detail.php?id=27219&keywords=&tid=0&lid=0", "peopleNum": "2", "positionType": "技术类", "workLocation": "深圳"}
{"positionName": "18435-高级反洗钱合规管理（深圳）", "publishTime": "2018-06-10", "positionLink": "position_detail.php?id=27275&keywords=&tid=0&lid=0", "peopleNum": "1", "positionType": "技术类", "workLocation": "深圳"}
{"positionName": "SA-腾讯社交广告微信公众号广告运营经理（微信广告 深圳）", "publishTime": "2018-06-10", "positionLink": "position_detail.php?id=27319&keywords=&tid=0&lid=0", "peopleNum": "1", "positionType": "产品/项目类", "workLocation": "深圳"}
{"positionName": "21309-在线教育ios高级开发工程师（深圳）", "publishTime": "2018-06-10", "positionLink": "position_detail.php?id=26702&keywords=&tid=0&lid=0", "peopleNum": "1", "positionType": "技术类", "workLocation": "深圳"}
{"positionName": "17467-高级品牌经理（深圳）", "publishTime": "2018-06-10", "positionLink": "position_detail.php?id=26969&keywords=&tid=0&lid=0", "peopleNum": "1", "positionType": "市场类", "workLocation": "深圳"}
{"positionName": "AQ-行业合作经理（北京）", "publishTime": "2018-06-10", "positionLink": "position_detail.php?id=26722&keywords=&tid=0&lid=0", "peopleNum": "1", "positionType": "职能类", "workLocation": "北京"}
{"positionName": "AQ-数据分析经理", "publishTime": "2018-06-10", "positionLink": "position_detail.php?id=26724&keywords=&tid=0&lid=0", "peopleNum": "2", "positionType": "职能类", "workLocation": "深圳"}
{"positionName": "WXG06-122 微信支付数据挖掘工程师（深圳）", "publishTime": "2018-06-10", "positionLink": "position_detail.php?id=27030&keywords=&tid=0&lid=0", "peopleNum": "1", "positionType": "技术类", "workLocation": "深圳"}
{"positionName": "CS-高级测试工程师", "publishTime": "2018-06-10", "positionLink": "position_detail.php?id=27054&keywords=&tid=0&lid=0", "peopleNum": "1", "positionType": "技术类", "workLocation": "深圳"}
{"positionName": "OMG236-腾讯视频ios测试工程师（深圳）", "publishTime": "2018-06-10", "positionLink": "position_detail.php?id=27895&keywords=&tid=0&lid=0", "peopleNum": "1", "positionType": "技术类", "workLocation": "深圳"}
{"positionName": "OMG236-视觉设计师（深圳）", "publishTime": "2018-06-10", "positionLink": "position_detail.php?id=27896&keywords=&tid=0&lid=0", "peopleNum": "2", "positionType": "设计类", "workLocation": "深圳"}
{"positionName": "23295-互娱媒介拓展经理（运营）（深圳）", "publishTime": "2018-06-10", "positionLink": "position_detail.php?id=27656&keywords=&tid=0&lid=0", "peopleNum": "1", "positionType": "市场类", "workLocation": "深圳"}
{"positionName": "15573-SLG类手游商业化策划（上海）", "publishTime": "2018-06-10", "positionLink": "position_detail.php?id=27722&keywords=&tid=0&lid=0", "peopleNum": "1", "positionType": "产品/项目类", "workLocation": "上海"}
{"positionName": "23295-互娱媒介拓展经理（深圳）", "publishTime": "2018-06-10", "positionLink": "position_detail.php?id=27492&keywords=&tid=0&lid=0", "peopleNum": "1", "positionType": "市场类", "workLocation": "深圳"}
{"positionName": "SNG03-互动视频高级web前端开发工程师（深圳）", "publishTime": "2018-06-10", "positionLink": "position_detail.php?id=27768&keywords=&tid=0&lid=0", "peopleNum": "1", "positionType": "技术类", "workLocation": "深圳"}
{"positionName": "18435-财付通高级风险分析师（深圳）", "publishTime": "2018-06-10", "positionLink": "position_detail.php?id=27785&keywords=&tid=0&lid=0", "peopleNum": "1", "positionType": "技术类", "workLocation": "深圳"}
{"positionName": "SA-腾讯社交广告创意经理(深圳)", "publishTime": "2018-06-10", "positionLink": "position_detail.php?id=27626&keywords=&tid=0&lid=0", "peopleNum": "3", "positionType": "市场类", "workLocation": "深圳"}
{"positionName": "SNG04-数据平台架构师", "publishTime": "2018-06-10", "positionLink": "position_detail.php?id=27627&keywords=&tid=0&lid=0", "peopleNum": "1", "positionType": "技术类", "workLocation": "上海"}
{"positionName": "TEG11-高级后台开发工程师（北京）", "publishTime": "2018-06-10", "positionLink": "position_detail.php?id=27410&keywords=&tid=0&lid=0", "peopleNum": "2", "positionType": "技术类", "workLocation": "北京"}
{"positionName": "21769-泛娱乐发行合作经理（北京）", "publishTime": "2018-06-10", "positionLink": "position_detail.php?id=27945&keywords=&tid=0&lid=0", "peopleNum": "3", "positionType": "市场类", "workLocation": "北京"}
{"positionName": "SNG01-QQ产品运营总监（深圳）", "publishTime": "2018-06-10", "positionLink": "position_detail.php?id=27979&keywords=&tid=0&lid=0", "peopleNum": "1", "positionType": "产品/项目类", "workLocation": "深圳"}
{"positionName": "TEG10-规划工程师(深圳)", "publishTime": "2018-06-10", "positionLink": "position_detail.php?id=28009&keywords=&tid=0&lid=0", "peopleNum": "1", "positionType": "技术类", "workLocation": "深圳"}
{"positionName": "SA-腾讯社交广告高级算法工程师（微信广告 深圳）", "publishTime": "2018-06-10", "positionLink": "position_detail.php?id=28047&keywords=&tid=0&lid=0", "peopleNum": "2", "positionType": "技术类", "workLocation": "深圳"}
{"positionName": "TEG15-Mysql数据库架构师（北京）", "publishTime": "2018-06-10", "positionLink": "position_detail.php?id=28051&keywords=&tid=0&lid=0", "peopleNum": "2", "positionType": "技术类", "workLocation": "北京"}
{"positionName": "OMG236-iOS开发工程师（深圳）", "publishTime": "2018-06-10", "positionLink": "position_detail.php?id=28139&keywords=&tid=0&lid=0", "peopleNum": "1", "positionType": "技术类", "workLocation": "深圳"}
{"positionName": "18435-反洗钱专家", "publishTime": "2018-06-10", "positionLink": "position_detail.php?id=27775&keywords=&tid=0&lid=0", "peopleNum": "1", "positionType": "技术类", "workLocation": "深圳"}
{"positionName": "WXG04-111 微信小游戏数据分析工程师（深圳、广州）", "publishTime": "2018-06-10", "positionLink": "position_detail.php?id=27791&keywords=&tid=0&lid=0", "peopleNum": "1", "positionType": "技术类", "workLocation": "广州"}
{"positionName": "OMG236-腾讯视频产品运营经理（深圳）", "publishTime": "2018-06-10", "positionLink": "position_detail.php?id=27805&keywords=&tid=0&lid=0", "peopleNum": "1", "positionType": "产品/项目类", "workLocation": "深圳"}
{"positionName": "OMG236-腾讯视频编码研发高级工程师（深圳）", "publishTime": "2018-06-10", "positionLink": "position_detail.php?id=27892&keywords=&tid=0&lid=0", "peopleNum": "1", "positionType": "技术类", "workLocation": "深圳"}
{"positionName": "MIG15-叮当闲聊算法研究员", "publishTime": "2018-06-10", "positionLink": "position_detail.php?id=28285&keywords=&tid=0&lid=0", "peopleNum": "1", "positionType": "技术类", "workLocation": "北京"}
{"positionName": "TEG14-mysql运维工程师（深圳）", "publishTime": "2018-06-10", "positionLink": "position_detail.php?id=28332&keywords=&tid=0&lid=0", "peopleNum": "1", "positionType": "技术类", "workLocation": "深圳"}
{"positionName": "TEG13-自然语言处理高级工程师（深圳）", "publishTime": "2018-06-10", "positionLink": "position_detail.php?id=28348&keywords=&tid=0&lid=0", "peopleNum": "1", "positionType": "技术类", "workLocation": "深圳"}
{"positionName": "TEG13-图像OCR算法工程师(北京)", "publishTime": "2018-06-10", "positionLink": "position_detail.php?id=28349&keywords=&tid=0&lid=0", "peopleNum": "1", "positionType": "技术类", "workLocation": "北京"}
{"positionName": "OMG236-iOS高级工程师（深圳）", "publishTime": "2018-06-10", "positionLink": "position_detail.php?id=28402&keywords=&tid=0&lid=0", "peopleNum": "1", "positionType": "技术类", "workLocation": "深圳"}
{"positionName": "25924-运营开发高级工程师（上海）", "publishTime": "2018-06-10", "positionLink": "position_detail.php?id=28170&keywords=&tid=0&lid=0", "peopleNum": "1", "positionType": "技术类", "workLocation": "上海"}
{"positionName": "SA-腾讯社交广告后台开发工程师（微信广告 深圳）", "publishTime": "2018-06-10", "positionLink": "position_detail.php?id=28193&keywords=&tid=0&lid=0", "peopleNum": "2", "positionType": "技术类", "workLocation": "深圳"}
{"positionName": "SNG06-QQ手游平台高级运营经理（深圳）", "publishTime": "2018-06-10", "positionLink": "position_detail.php?id=28196&keywords=&tid=0&lid=0", "peopleNum": "1", "positionType": "产品/项目类", "workLocation": "深圳"}
{"positionName": "18435-风控后台开发工程师（深圳）", "publishTime": "2018-06-10", "positionLink": "position_detail.php?id=28080&keywords=&tid=0&lid=0", "peopleNum": "1", "positionType": "技术类", "workLocation": "深圳"}
{"positionName": "OMG236-视频编解码研发专家（深圳）", "publishTime": "2018-06-10", "positionLink": "position_detail.php?id=28140&keywords=&tid=0&lid=0", "peopleNum": "1", "positionType": "技术类", "workLocation": "深圳"}
{"positionName": "19823-动画电影美术设计师（深圳）", "publishTime": "2018-06-10", "positionLink": "position_detail.php?id=24992&keywords=&tid=0&lid=0", "peopleNum": "1", "positionType": "设计类", "workLocation": "深圳"}
{"positionName": "OMG236-腾讯视频媒资库后台开发高级工程师（深圳）", "publishTime": "2018-06-10", "positionLink": "position_detail.php?id=25779&keywords=&tid=0&lid=0", "peopleNum": "2", "positionType": "技术类", "workLocation": "深圳"}
{"positionName": "15612-高级场景原画设计师（北京）", "publishTime": "2018-06-10", "positionLink": "position_detail.php?id=25808&keywords=&tid=0&lid=0", "peopleNum": "1", "positionType": "设计类", "workLocation": "北京"}
{"positionName": "20762-政府事务经理(北京)", "publishTime": "2018-06-10", "positionLink": "position_detail.php?id=26070&keywords=&tid=0&lid=0", "peopleNum": "1", "positionType": "职能类", "workLocation": "北京"}
{"positionName": "S2-财经外联与拓展经理（深圳）", "publishTime": "2018-06-10", "positionLink": "position_detail.php?id=25849&keywords=&tid=0&lid=0", "peopleNum": "1", "positionType": "职能类", "workLocation": "深圳"}
{"positionName": "18428-财付通清算业务测试工程师（深圳）", "publishTime": "2018-06-10", "positionLink": "position_detail.php?id=24411&keywords=&tid=0&lid=0", "peopleNum": "1", "positionType": "技术类", "workLocation": "深圳"}
{"positionName": "15573-天天酷跑资深游戏策划（上海）", "publishTime": "2018-06-10", "positionLink": "position_detail.php?id=24929&keywords=&tid=0&lid=0", "peopleNum": "2", "positionType": "产品/项目类", "workLocation": "上海"}
{"positionName": "TEG09-存储运维工程师（深圳）", "publishTime": "2018-06-10", "positionLink": "position_detail.php?id=23692&keywords=&tid=0&lid=0", "peopleNum": "1", "positionType": "技术类", "workLocation": "深圳"}
{"positionName": "SA-腾讯社交广告产品运营经理（生态平台业务）", "publishTime": "2018-06-10", "positionLink": "position_detail.php?id=24511&keywords=&tid=0&lid=0", "peopleNum": "1", "positionType": "产品/项目类", "workLocation": "上海"}
{"positionName": "OMG236-腾讯视频测试开发工程师（深圳）", "publishTime": "2018-06-10", "positionLink": "position_detail.php?id=23583&keywords=&tid=0&lid=0", "peopleNum": "2", "positionType": "技术类", "workLocation": "深圳"}
{"positionName": "MIG16-腾讯地图iOS客户端高级工程师（北京）", "publishTime": "2018-06-10", "positionLink": "position_detail.php?id=41323&keywords=&tid=0&lid=0", "peopleNum": "1", "positionType": "技术类", "workLocation": "北京"}
{"positionName": "15575-QQ飞车手游服务器开发工程师（成都）", "publishTime": "2018-06-10", "positionLink": "position_detail.php?id=41324&keywords=&tid=0&lid=0", "peopleNum": "1", "positionType": "技术类", "workLocation": "成都"}
{"positionName": "22025-UE4游戏高级研发工程师（深圳）", "publishTime": "2018-06-10", "positionLink": "position_detail.php?id=41309&keywords=&tid=0&lid=0", "peopleNum": "3", "positionType": "技术类", "workLocation": "深圳"}
{"positionName": "18302-Unity动作游戏资深工程师（深圳）", "publishTime": "2018-06-10", "positionLink": "position_detail.php?id=41311&keywords=&tid=0&lid=0", "peopleNum": "1", "positionType": "技术类", "workLocation": "深圳"}
{"positionName": "18302-Unity 动作游戏引擎工程师（深圳）", "publishTime": "2018-06-10", "positionLink": "position_detail.php?id=41312&keywords=&tid=0&lid=0", "peopleNum": "1", "positionType": "技术类", "workLocation": "深圳"}
{"positionName": "18924-SNG高管秘书（深圳）", "publishTime": "2018-06-10", "positionLink": "position_detail.php?id=41313&keywords=&tid=0&lid=0", "peopleNum": "1", "positionType": "职能类", "workLocation": "深圳"}
{"positionName": "26564-高级iOS开发工程师(深圳)", "publishTime": "2018-06-10", "positionLink": "position_detail.php?id=41314&keywords=&tid=0&lid=0", "peopleNum": "1", "positionType": "技术类", "workLocation": "深圳"}
{"positionName": "SA-腾讯社交广告数据应用产品经理（北京）", "publishTime": "2018-06-10", "positionLink": "position_detail.php?id=41316&keywords=&tid=0&lid=0", "peopleNum": "1", "positionType": "产品/项目类", "workLocation": "北京"}
{"positionName": "15618-场景原画设计师（上海）", "publishTime": "2018-06-10", "positionLink": "position_detail.php?id=41318&keywords=&tid=0&lid=0", "peopleNum": "2", "positionType": "设计类", "workLocation": "上海"}
{"positionName": "17520-互娱项目管理经理（深圳）", "publishTime": "2018-06-10", "positionLink": "position_detail.php?id=41303&keywords=&tid=0&lid=0", "peopleNum": "1", "positionType": "产品/项目类", "workLocation": "深圳"}
{"positionName": "18797-游戏运营高级项目经理（深圳）", "publishTime": "2018-06-10", "positionLink": "position_detail.php?id=41325&keywords=&tid=0&lid=0", "peopleNum": "1", "positionType": "产品/项目类", "workLocation": "深圳"}
{"positionName": "SD3-刺激战场全球版前台开发工程师(深圳)", "publishTime": "2018-06-10", "positionLink": "position_detail.php?id=41326&keywords=&tid=0&lid=0", "peopleNum": "2", "positionType": "技术类", "workLocation": "深圳"}
{"positionName": "SNG16-全民K歌活动运营（深圳）", "publishTime": "2018-06-10", "positionLink": "position_detail.php?id=41327&keywords=&tid=0&lid=0", "peopleNum": "1", "positionType": "产品/项目类", "workLocation": "深圳"}
{"positionName": "20503-硬件合作研发工程师（上海）", "publishTime": "2018-06-10", "positionLink": "position_detail.php?id=41329&keywords=&tid=0&lid=0", "peopleNum": "3", "positionType": "技术类", "workLocation": "上海"}
{"positionName": "SA-腾讯社交广告社交洞察（高级）经理（深圳）", "publishTime": "2018-06-10", "positionLink": "position_detail.php?id=41315&keywords=&tid=0&lid=0", "peopleNum": "1", "positionType": "市场类", "workLocation": "深圳"}
{"positionName": "18402-MMO类版本管理（深圳）", "publishTime": "2018-06-10", "positionLink": "position_detail.php?id=41317&keywords=&tid=0&lid=0", "peopleNum": "1", "positionType": "产品/项目类", "workLocation": "深圳"}
{"positionName": "21089-文学编辑方向高级IP经理（深圳）", "publishTime": "2018-06-10", "positionLink": "position_detail.php?id=41319&keywords=&tid=0&lid=0", "peopleNum": "1", "positionType": "产品/项目类", "workLocation": "深圳"}
{"positionName": "21089-影视方向高级IP经理（深圳）", "publishTime": "2018-06-10", "positionLink": "position_detail.php?id=41320&keywords=&tid=0&lid=0", "peopleNum": "1", "positionType": "产品/项目类", "workLocation": "深圳"}
{"positionName": "20772-腾讯视频纯网综艺制片人（北京）", "publishTime": "2018-06-10", "positionLink": "position_detail.php?id=41321&keywords=&tid=0&lid=0", "peopleNum": "2", "positionType": "市场类", "workLocation": "北京"}
{"positionName": "16175-游戏项目经理（深圳）", "publishTime": "2018-06-10", "positionLink": "position_detail.php?id=41322&keywords=&tid=0&lid=0", "peopleNum": "1", "positionType": "产品/项目类", "workLocation": "深圳"}
{"positionName": "22851-腾讯视频电视剧内容评估", "publishTime": "2018-06-10", "positionLink": "position_detail.php?id=41338&keywords=&tid=0&lid=0", "peopleNum": "1", "positionType": "内容编辑类", "workLocation": "北京"}
{"positionName": "S2-财付通资金结算岗(深圳)", "publishTime": "2018-06-10", "positionLink": "position_detail.php?id=41339&keywords=&tid=0&lid=0", "peopleNum": "1", "positionType": "职能类", "workLocation": "深圳"}
{"positionName": "AQ-刑事法律研究经理（北京）", "publishTime": "2018-06-10", "positionLink": "position_detail.php?id=41340&keywords=&tid=0&lid=0", "peopleNum": "2", "positionType": "职能类", "workLocation": "北京"}
{"positionName": "21309-腾讯课堂职业考证类目经理（深圳）", "publishTime": "2018-06-10", "positionLink": "position_detail.php?id=41342&keywords=&tid=0&lid=0", "peopleNum": "1", "positionType": "产品/项目类", "workLocation": "深圳"}
{"positionName": "25663-医疗云高级产品经理（深圳）", "publishTime": "2018-06-10", "positionLink": "position_detail.php?id=41328&keywords=&tid=0&lid=0", "peopleNum": "1", "positionType": "产品/项目类", "workLocation": "深圳"}
{"positionName": "SNG16-全民K歌iOS开发工程师（深圳）", "publishTime": "2018-06-10", "positionLink": "position_detail.php?id=41330&keywords=&tid=0&lid=0", "peopleNum": "3", "positionType": "技术类", "workLocation": "深圳"}
{"positionName": "SNG11-高级数据分析师（深圳）", "publishTime": "2018-06-10", "positionLink": "position_detail.php?id=41331&keywords=&tid=0&lid=0", "peopleNum": "2", "positionType": "技术类", "workLocation": "深圳"}
{"positionName": "23294-互娱品牌组长（深圳）", "publishTime": "2018-06-10", "positionLink": "position_detail.php?id=41332&keywords=&tid=0&lid=0", "peopleNum": "2", "positionType": "市场类", "workLocation": "深圳"}
{"positionName": "23516-战略规划/市场分析经理（深圳）", "publishTime": "2018-06-10", "positionLink": "position_detail.php?id=41333&keywords=&tid=0&lid=0", "peopleNum": "3", "positionType": "市场类", "workLocation": "深圳"}
{"positionName": "27730-短视频拍摄功能产品经理（深圳）", "publishTime": "2018-06-10", "positionLink": "position_detail.php?id=41336&keywords=&tid=0&lid=0", "peopleNum": "2", "positionType": "产品/项目类", "workLocation": "深圳"}
{"positionName": "SNG16-腾讯音乐Android高级工程师（深圳）", "publishTime": "2018-06-10", "positionLink": "position_detail.php?id=41419&keywords=&tid=0&lid=0", "peopleNum": "10", "positionType": "技术类", "workLocation": "深圳"}
{"positionName": "SNG16-腾讯音乐web前端开发工程师（深圳）", "publishTime": "2018-06-10", "positionLink": "position_detail.php?id=41421&keywords=&tid=0&lid=0", "peopleNum": "5", "positionType": "技术类", "workLocation": "深圳"}
{"positionName": "SNG16-腾讯音乐系统测试工程师（深圳）", "publishTime": "2018-06-10", "positionLink": "position_detail.php?id=41422&keywords=&tid=0&lid=0", "peopleNum": "5", "positionType": "技术类", "workLocation": "深圳"}
{"positionName": "SNG16-腾讯音乐专项测试开发工程师（深圳）", "publishTime": "2018-06-10", "positionLink": "position_detail.php?id=41423&keywords=&tid=0&lid=0", "peopleNum": "5", "positionType": "技术类", "workLocation": "深圳"}
{"positionName": "TEG05-高级业务运维工程师（深圳）", "publishTime": "2018-06-10", "positionLink": "position_detail.php?id=41412&keywords=&tid=0&lid=0", "peopleNum": "1", "positionType": "技术类", "workLocation": "深圳"}
{"positionName": "MIG12-运营开发工程师（深圳）", "publishTime": "2018-06-10", "positionLink": "position_detail.php?id=41414&keywords=&tid=0&lid=0", "peopleNum": "2", "positionType": "技术类", "workLocation": "深圳"}
{"positionName": "SA-腾讯社交广告后台安全开发工程师（北京）", "publishTime": "2018-06-10", "positionLink": "position_detail.php?id=41415&keywords=&tid=0&lid=0", "peopleNum": "1", "positionType": "技术类", "workLocation": "北京"}
{"positionName": "SNG16-腾讯音乐资深内容编辑（深圳）", "publishTime": "2018-06-10", "positionLink": "position_detail.php?id=41416&keywords=&tid=0&lid=0", "peopleNum": "1", "positionType": "产品/项目类", "workLocation": "深圳"}
{"positionName": "SNG16-腾讯音乐后台开发工程师（深圳）", "publishTime": "2018-06-10", "positionLink": "position_detail.php?id=41417&keywords=&tid=0&lid=0", "peopleNum": "20", "positionType": "技术类", "workLocation": "深圳"}
{"positionName": "SNG16-腾讯音乐视频类新产品后台开发工程师（深圳）", "publishTime": "2018-06-10", "positionLink": "position_detail.php?id=41418&keywords=&tid=0&lid=0", "peopleNum": "5", "positionType": "技术类", "workLocation": "深圳"}
{"positionName": "MIG07-电脑管家客户端开发工程师（深圳）", "publishTime": "2018-06-10", "positionLink": "position_detail.php?id=28571&keywords=&tid=0&lid=0", "peopleNum": "2", "positionType": "技术类", "workLocation": "深圳"}
{"positionName": "SNG06-企鹅电竞高级主播运营经理（深圳）", "publishTime": "2018-06-10", "positionLink": "position_detail.php?id=28417&keywords=&tid=0&lid=0", "peopleNum": "1", "positionType": "产品/项目类", "workLocation": "深圳"}
{"positionName": "15573-资深手游运营经理（上海）", "publishTime": "2018-06-10", "positionLink": "position_detail.php?id=28418&keywords=&tid=0&lid=0", "peopleNum": "1", "positionType": "产品/项目类", "workLocation": "上海"}
{"positionName": "SNG06-企鹅电竞商业化运营经理（深圳）", "publishTime": "2018-06-10", "positionLink": "position_detail.php?id=28421&keywords=&tid=0&lid=0", "peopleNum": "1", "positionType": "产品/项目类", "workLocation": "深圳"}
{"positionName": "SNG06-企鹅电竞直播运营经理（深圳）", "publishTime": "2018-06-10", "positionLink": "position_detail.php?id=28422&keywords=&tid=0&lid=0", "peopleNum": "2", "positionType": "产品/项目类", "workLocation": "深圳"}
{"positionName": "SNG06-企鹅电竞赛事运营经理（深圳）", "publishTime": "2018-06-10", "positionLink": "position_detail.php?id=28424&keywords=&tid=0&lid=0", "peopleNum": "1", "positionType": "产品/项目类", "workLocation": "深圳"}
{"positionName": "21229-高级游戏业务商业分析经理（上海）", "publishTime": "2018-06-10", "positionLink": "position_detail.php?id=28455&keywords=&tid=0&lid=0", "peopleNum": "1", "positionType": "产品/项目类", "workLocation": "上海"}
{"positionName": "21229-高级游戏市场产品分析（深圳）", "publishTime": "2018-06-10", "positionLink": "position_detail.php?id=28531&keywords=&tid=0&lid=0", "peopleNum": "1", "positionType": "产品/项目类", "workLocation": "深圳"}
{"positionName": "21229-高级游戏市场产品分析（上海）", "publishTime": "2018-06-10", "positionLink": "position_detail.php?id=28532&keywords=&tid=0&lid=0", "peopleNum": "1", "positionType": "产品/项目类", "workLocation": "上海"}
{"positionName": "18428-腾讯金融业务高级研发工程师(深圳)", "publishTime": "2018-06-10", "positionLink": "position_detail.php?id=28239&keywords=&tid=0&lid=0", "peopleNum": "2", "positionType": "技术类", "workLocation": "深圳"}
{"positionName": "SA-腾讯社交广告产品渠道运营经理（品牌渠道）（上海）", "publishTime": "2018-06-10", "positionLink": "position_detail.php?id=28942&keywords=&tid=0&lid=0", "peopleNum": "2", "positionType": "产品/项目类", "workLocation": "上海"}
{"positionName": "SA-腾讯社交广告客户运营经理（汽车行业）", "publishTime": "2018-06-10", "positionLink": "position_detail.php?id=28945&keywords=&tid=0&lid=0", "peopleNum": "1", "positionType": "产品/项目类", "workLocation": "北京"}
{"positionName": "SA-腾讯社交广告KA效果广告产品运营经理（深圳）", "publishTime": "2018-06-10", "positionLink": "position_detail.php?id=28768&keywords=&tid=0&lid=0", "peopleNum": "1", "positionType": "产品/项目类", "workLocation": "深圳"}
{"positionName": "TEG03-高级算法研发工程师（深圳）", "publishTime": "2018-06-10", "positionLink": "position_detail.php?id=28858&keywords=&tid=0&lid=0", "peopleNum": "1", "positionType": "技术类", "workLocation": "深圳"}
{"positionName": "15573-资深手游运营策划（上海）", "publishTime": "2018-06-10", "positionLink": "position_detail.php?id=28918&keywords=&tid=0&lid=0", "peopleNum": "1", "positionType": "产品/项目类", "workLocation": "上海"}
{"positionName": "16811-授权拓展经理", "publishTime": "2018-06-10", "positionLink": "position_detail.php?id=28674&keywords=&tid=0&lid=0", "peopleNum": "1", "positionType": "市场类", "workLocation": "北京"}
{"positionName": "OMG236-视频推荐算法工程师(北京)", "publishTime": "2018-06-10", "positionLink": "position_detail.php?id=28718&keywords=&tid=0&lid=0", "peopleNum": "1", "positionType": "技术类", "workLocation": "北京"}
{"positionName": "OMG236-视频推荐数据开发工程师（深圳）", "publishTime": "2018-06-10", "positionLink": "position_detail.php?id=28722&keywords=&tid=0&lid=0", "peopleNum": "1", "positionType": "技术类", "workLocation": "深圳"}
{"positionName": "OMG236-推荐算法工程师（深圳）", "publishTime": "2018-06-10", "positionLink": "position_detail.php?id=28724&keywords=&tid=0&lid=0", "peopleNum": "1", "positionType": "技术类", "workLocation": "深圳"}
{"positionName": "OMG236-腾讯视频OTT&腾讯智慧家庭产品经理（深圳）", "publishTime": "2018-06-10", "positionLink": "position_detail.php?id=28726&keywords=&tid=0&lid=0", "peopleNum": "1", "positionType": "产品/项目类", "workLocation": "深圳"}
{"positionName": "MIG03-测试开发工程师（广州）", "publishTime": "2018-06-10", "positionLink": "position_detail.php?id=29587&keywords=&tid=0&lid=0", "peopleNum": "1", "positionType": "技术类", "workLocation": "广州"}
{"positionName": "SA-腾讯社交广告KA效果广告行业运营经理（北京）", "publishTime": "2018-06-10", "positionLink": "position_detail.php?id=29434&keywords=&tid=0&lid=0", "peopleNum": "2", "positionType": "产品/项目类", "workLocation": "北京"}
{"positionName": "SA-腾讯社交广告快消零售行业产品运营（大客户运营）（上海）", "publishTime": "2018-06-10", "positionLink": "position_detail.php?id=29435&keywords=&tid=0&lid=0", "peopleNum": "2", "positionType": "产品/项目类", "workLocation": "北京"}
{"positionName": "23674-新闻短视频推荐算法组长", "publishTime": "2018-06-10", "positionLink": "position_detail.php?id=29209&keywords=&tid=0&lid=0", "peopleNum": "1", "positionType": "技术类", "workLocation": "北京"}
{"positionName": "TEG13-后台开发工程师（深圳）", "publishTime": "2018-06-10", "positionLink": "position_detail.php?id=29011&keywords=&tid=0&lid=0", "peopleNum": "2", "positionType": "技术类", "workLocation": "深圳"}
{"positionName": "MIG03-腾讯后台开发工程师（深圳）", "publishTime": "2018-06-10", "positionLink": "position_detail.php?id=29026&keywords=&tid=0&lid=0", "peopleNum": "1", "positionType": "技术类", "workLocation": "深圳"}
{"positionName": "23294-互娱品牌经理(上海)", "publishTime": "2018-06-10", "positionLink": "position_detail.php?id=29044&keywords=&tid=0&lid=0", "peopleNum": "1", "positionType": "市场类", "workLocation": "上海"}
{"positionName": "27193-互娱视觉设计师", "publishTime": "2018-06-10", "positionLink": "position_detail.php?id=29107&keywords=&tid=0&lid=0", "peopleNum": "1", "positionType": "设计类", "workLocation": "深圳"}
{"positionName": "16810-移动内容编辑（北京）", "publishTime": "2018-06-10", "positionLink": "position_detail.php?id=29150&keywords=&tid=0&lid=0", "peopleNum": "3", "positionType": "内容编辑类", "workLocation": "北京"}
{"positionName": "SA-腾讯社交广告营销策划经理（上海）", "publishTime": "2018-06-10", "positionLink": "position_detail.php?id=28939&keywords=&tid=0&lid=0", "peopleNum": "1", "positionType": "市场类", "workLocation": "上海"}
{"positionName": "21062-技术美术专家（上海）", "publishTime": "2018-06-10", "positionLink": "position_detail.php?id=29697&keywords=&tid=0&lid=0", "peopleNum": "1", "positionType": "设计类", "workLocation": "上海"}
{"positionName": "OMG236-视频数据挖掘高级工程师（深圳）", "publishTime": "2018-06-10", "positionLink": "position_detail.php?id=29710&keywords=&tid=0&lid=0", "peopleNum": "1", "positionType": "技术类", "workLocation": "深圳"}
{"positionName": "TEG13-接入后台开发工程师（深圳）", "publishTime": "2018-06-10", "positionLink": "position_detail.php?id=29489&keywords=&tid=0&lid=0", "peopleNum": "1", "positionType": "技术类", "workLocation": "深圳"}
{"positionName": "SNG11-QQ业务高级技术运营工程师（深圳）", "publishTime": "2018-06-10", "positionLink": "position_detail.php?id=29834&keywords=&tid=0&lid=0", "peopleNum": "1", "positionType": "技术类", "workLocation": "深圳"}
{"positionName": "15612-游戏客户端开发(北京）", "publishTime": "2018-06-10", "positionLink": "position_detail.php?id=29617&keywords=&tid=0&lid=0", "peopleNum": "1", "positionType": "技术类", "workLocation": "北京"}
{"positionName": "SA-腾讯社交广告SMB行业运营经理（北京）（教育行业）", "publishTime": "2018-06-10", "positionLink": "position_detail.php?id=29674&keywords=&tid=0&lid=0", "peopleNum": "2", "positionType": "市场类", "workLocation": "北京"}
{"positionName": "SNG04-推荐工程师（深圳）", "publishTime": "2018-06-10", "positionLink": "position_detail.php?id=29478&keywords=&tid=0&lid=0", "peopleNum": "1", "positionType": "技术类", "workLocation": "深圳"}
{"positionName": "AQ-法律合作研究经理（深圳）", "publishTime": "2018-06-10", "positionLink": "position_detail.php?id=29304&keywords=&tid=0&lid=0", "peopleNum": "1", "positionType": "职能类", "workLocation": "深圳"}
{"positionName": "TEG07-高级web前端开发工程师（深圳）", "publishTime": "2018-06-10", "positionLink": "position_detail.php?id=29305&keywords=&tid=0&lid=0", "peopleNum": "1", "positionType": "技术类", "workLocation": "深圳"}
{"positionName": "AQ-安全智库经理（深圳）", "publishTime": "2018-06-10", "positionLink": "position_detail.php?id=29315&keywords=&tid=0&lid=0", "peopleNum": "1", "positionType": "职能类", "workLocation": "深圳"}
